modmailtranslation/Translator.py
modmailtranslation/__init__.py
modmailtranslation-1.1.0.dist-info/LICENSE
modmailtranslation-1.1.0.dist-info/METADATA
modmailtranslation-1.1.0.dist-info/WHEEL
modmailtranslation-1.1.0.dist-info/top_level.txt
modmailtranslation-1.1.0.dist-info/RECORD
